tcolors/__init__.py
tcolors/colorizer.py
tcolors/styles.py
tcolors-0.1.0.dist-info/LICENSE
tcolors-0.1.0.dist-info/METADATA
tcolors-0.1.0.dist-info/WHEEL
tcolors-0.1.0.dist-info/top_level.txt
tcolors-0.1.0.dist-info/RECORD
