Metadata-Version: 2.1
Name: tcolors
Version: 0.1.0
Summary: Yet another Python library to work with ANSI colors in the terminal
Home-page: https://github.com/albertoalcolea/tcolors
Author: Alberto Alcolea
Author-email: albertoalcolea@gmail.com
License: MIT
Project-URL: Source, https://github.com/albertoalcolea/tcolors
Keywords: tcolors,tcolor,term,terminal,CLI,color,colors,colour,colours,ANSI,ANSI color,ANSI colors,ANSI colour,ANSI colours
Classifier: Development Status :: 5 - Production/Stable
Classifier: Environment :: Console
Classifier: Intended Audience :: Developers
Classifier: License :: OSI Approved :: MIT License
Classifier: Operating System :: OS Independent
Classifier: Programming Language :: Python
Classifier: Programming Language :: Python :: 3
Classifier: Programming Language :: Python :: 3.6
Classifier: Programming Language :: Python :: 3.7
Classifier: Programming Language :: Python :: 3.8
Classifier: Programming Language :: Python :: 3.9
Classifier: Programming Language :: Python :: 3.10
Classifier: Programming Language :: Python :: 3.11
Classifier: Programming Language :: Python :: 3.12
Classifier: Programming Language :: Python :: 3 :: Only
Classifier: Programming Language :: Python :: Implementation :: CPython
Classifier: Programming Language :: Python :: Implementation :: PyPy
Classifier: Topic :: Terminals
Requires-Python: >=3.6
License-File: LICENSE
Provides-Extra: dev
Requires-Dist: flake8 >=4.0.1 ; extra == 'dev'
Requires-Dist: tox >=3.25.0 ; extra == 'dev'
Requires-Dist: twine >=4.0.0 ; extra == 'dev'
